{"User.b46b0752-6372-49f2-a08e-fe8431d31fb8": {"id": "b46b0752-6372-49f2-a08e-fe8431d31fb8", "created_at": "2023-03-23T10:41:33.864290", "updated_at": "2023-03-23T10:41:33.864340", "__class__": "User"}, "User.ae7901cc-a1e1-4ed4-b6b1-87677a10872c": {"id": "ae7901cc-a1e1-4ed4-b6b1-87677a10872c", "created_at": "2023-03-23T10:44:13.122215", "updated_at": "2023-03-23T10:44:13.122265", "__class__": "User"}, "State.3be434d5-f3b4-4849-87a6-bccb91bf7955": {"id": "3be434d5-f3b4-4849-87a6-bccb91bf7955", "created_at": "2023-03-23T11:08:00.113067", "updated_at": "2023-03-23T11:08:00.113189", "name": "California", "__class__": "State"}, "State.efac6760-d7e1-4a43-81e5-0fd360a0e44f": {"id": "efac6760-d7e1-4a43-81e5-0fd360a0e44f", "created_at": "2023-03-23T11:08:00.136855", "updated_at": "2023-03-23T11:08:00.137011", "name": "Arizona", "__class__": "State"}, "Place.f5102752-9576-4cf1-882c-8500c954a1a1": {"id": "f5102752-9576-4cf1-882c-8500c954a1a1", "created_at": "2023-03-23T11:08:00.149752", "updated_at": "2023-03-23T11:08:00.150023", "city_id": "0001", "user_id": "0001", "name": "My little house", "number_rooms": 4, "number_bathrooms": 2, "max_guest": 10, "price_by_night": 300, "latitude": 37.773972, "longitude": -122.431297, "__class__": "Place"}, "State.523c7d38-51be-428d-8f79-f943df4acbf2": {"id": "523c7d38-51be-428d-8f79-f943df4acbf2", "created_at": "2023-03-23T11:08:24.609848", "updated_at": "2023-03-23T11:08:24.609918", "name": "California", "__class__": "State"}, "State.bdc6f0fb-720c-4ce3-85f9-397942a8a64a": {"id": "bdc6f0fb-720c-4ce3-85f9-397942a8a64a", "created_at": "2023-03-23T11:08:24.616811", "updated_at": "2023-03-23T11:08:24.616929", "name": "Arizona", "__class__": "State"}, "Place.344006ff-0e06-4b5b-9f49-9733553f1809": {"id": "344006ff-0e06-4b5b-9f49-9733553f1809", "created_at": "2023-03-23T11:08:24.642818", "updated_at": "2023-03-23T11:08:24.643125", "city_id": "0001", "user_id": "0001", "name": "My little house", "number_rooms": 4, "number_bathrooms": 2, "max_guest": 10, "price_by_night": 300, "latitude": 37.773972, "longitude": -122.431297, "__class__": "Place"}}